{
  "slug": "monhun_rise",
  "updated": "2026-03-28",
  "lead": "モンスターハンターライズはアデリオン製のスマスロAT機。天井はゲーム数999G+前兆で赤7以上確定、クエストスルー天井6スルーで7回目赤7以上確定。カムラポイント天井もあり。小役確率に設定差なし。",
  "summaryBoxes": [
    {
      "label": "天井",
      "value": "999G"
    },
    {
      "label": "スルー天井",
      "value": "6スルー"
    },
    {
      "label": "狙い目",
      "value": "等価660G〜"
    },
    {
      "label": "ヤメ時",
      "value": "AT後1G"
    }
  ],
  "factTable": [
    [
      "ゲーム数天井",
      "999G+前兆（赤7以上確定）"
    ],
    [
      "スルー天井",
      "6スルー（7回目赤7以上確定）"
    ],
    [
      "カムラポイント天井",
      "380pt〜"
    ],
    [
      "狙い目（等価）",
      "660G〜 / 5スルー〜"
    ],
    [
      "機械割（設定1）",
      "97.9%"
    ],
    [
      "機械割（設定6）",
      "114.3%"
    ],
    [
      "AT純増",
      "約2.7枚/G"
    ]
  ],
  "sections": [
    {
      "title": "天井・恩恵",
      "body": [
        "天井：999G+前兆（AT間）→ 赤7ボーナス以上確定",
        "スルー天井：クエスト6スルー（7回目赤7以上確定）",
        "カムラポイント天井：規定ポイント到達でクエスト発生",
        "リセット短縮：ポイントモードB以上濃厚、クエストテーブル優遇"
      ]
    },
    {
      "title": "狙い目",
      "body": [
        "カムラポイント天井は380pt〜で到達するとCZ確定。",
        "等価なら660G〜が狙い目ライン。5スルー以上なら即打ちOK。"
      ]
    },
    {
      "title": "ヤメ時",
      "body": [
        "AT終了後1Gで画面を確認してヤメ。レア役が成立した場合はフォローしてください。",
        "BGMがサマーVerに変化した場合は天国濃厚のため続行。"
      ]
    },
    {
      "title": "狙い目の根拠",
      "body": [
        "AT間天井999G+前兆で赤7ボーナス以上確定。等価交換の期待値プラス圏は660G〜で、天井近辺ほど期待値が高まる。スルー天井は6スルーで7回目赤7以上確定のため、5スルー以上なら即打ちOK。",
        "カムラポイントが380pt前後ある台はCZ確定のため、ポイント残量の確認が重要な判断材料になる。設定6の機械割は114.3%と高く、天井狙いと設定狙いが両立しやすい機種。"
      ]
    },
    {
      "title": "ヤメ時の判断",
      "body": [
        "AT終了後1G目に画面を確認してヤメが基本。レア役が成立した場合はフォローが必要。BGMがサマーVer.に変化した場合は天国滞在が濃厚なため続行推奨。",
        "設定示唆（エンタトロフィー虹＝設定6濃厚）を確認した場合は、天井狙いから設定狙いに切り替えて続行を検討する。スルー回数が残っている場合も天国移行まで続行価値がある。"
      ]
    },
    {
      "title": "立ち回りのコツ",
      "body": [
        "着席前に必ずカムラポイントとスルー回数を確認する。ポイントが300pt超えの台や5スルー以上の台は即打ち候補として優先的に確保したい。",
        "小役確率に設定差がないためポチポチくんは非対応。設定判別はエンタトロフィーや初当り確率・AT当選率の積み重ねで判断していく。"
      ]
    },
    {
      "title": "設定示唆まとめ",
      "type": "settei",
      "rows": [
        [
          "エンタトロフィー 銅",
          "設定2以上"
        ],
        [
          "エンタトロフィー 銀",
          "設定3以上"
        ],
        [
          "エンタトロフィー 金",
          "設定4以上"
        ],
        [
          "エンタトロフィー 紅葉",
          "設定5以上"
        ],
        [
          "エンタトロフィー 虹",
          "設定6濃厚"
        ]
      ]
    }
  ],
  "evTable": [
    {
      "range": "0〜499G",
      "verdict": "まだ早い"
    },
    {
      "range": "500〜659G",
      "verdict": "様子見"
    },
    {
      "range": "660〜849G",
      "verdict": "狙い目"
    },
    {
      "range": "850G〜",
      "verdict": "積極的"
    }
  ]
}