{
  "slug": "sf5",
  "updated": "2026-03-20",
  "lead": "SF5は天井がありません。 ゲーム数狙いには向きません。 設定狙い向けの機種です。",
  "summaryBoxes": [
    {
      "label": "基本方針",
      "value": "設定狙い主体"
    },
    {
      "label": "チェッカー表示",
      "value": "ゲーム数判定は出さない"
    },
    {
      "label": "設定判別",
      "value": "ポチポチくんへ移動"
    },
    {
      "label": "見るポイント",
      "value": "初当たり  小役  各種示唆"
    }
  ],
  "factTable": [
    [
      "機械割（設定1）",
      "97.7%"
    ],
    [
      "ページの役割",
      "設定狙い向けの案内ページ"
    ],
    [
      "ゲーム数狙い",
      "天井なしのため非対応"
    ],
    [
      "おすすめツール",
      "小役カウンター ポチポチくん"
    ],
    [
      "見る要素",
      "初当たり 小役 示唆画面"
    ]
  ],
  "sections": [
    {
      "title": "天井・恩恵",
      "body": [
        "天井なし（ノーマルタイプ）。設定狙い専用の機種です。"
      ]
    },
    {
      "title": "狙い目の根拠",
      "body": [
        "スマスロストリートファイターVはノーマルタイプ（天井なし）のため、ゲーム数による期待値計算は存在しません。設定狙い専用の機種で、高設定が見込めるホール・イベント日への集中稼働が基本戦略です。",
        "初当り確率や各種示唆演出を積み重ねて設定を推測し、高設定と判断できる台に長く座ることで収益を上げる機種です。ゲーム数だけで判断しようとすると期待値計算ができない点に注意してください。",
        "設定1の機械割は**97.7%**、設定4で**104.0%**前後と推定されており、設定4以上をつかめれば長時間稼働で十分プラス収支を狙えるスペックです。スイカ確率に設定差があり、スイカ成立時の直撃ボーナス当選率にも大きな設定差が存在するため、スイカ後の挙動も判別要素として注目できます。",
        "BATTLE BONUS終了時の高確・超高確移行率にも設定差が大きく、ボーナス後のステージ移行（高確示唆ステージへの突入率）が高設定判別の重要な指標になります。複数のBB終了後に高確以上が連発する台は粘る価値が大きいです。"
      ]
    },
    {
      "title": "ヤメ時の判断",
      "body": [
        "天井管理がないためヤメ時の制約は薄いです。設定狙いとして打っている場合は、ボーナス・AT終了後の設定示唆画面を全て回収してから離席するのが基本です。",
        "低設定確定演出を確認した時点でヤメを検討しましょう。逆に高設定の根拠が積み重なっているなら継続が有効で、ポチポチくんで数値を管理しながら判断精度を上げていきます。",
        "トロフィー演出が出ない・スイカからの直撃ボーナス当選が薄い・BB終了後のステージ移行が低確中心、というネガ要素が複数重なった場合は設定1〜2濃厚として撤退判断ができます。3000〜5000G程度のサンプルを蓄積した上での判断が安全です。",
        "逆に紅葉柄トロフィー（設定5以上濃厚）や虹トロフィー（設定6濃厚）といった強い示唆が出た場合は、根拠が崩れない限り閉店まで続行する判断が基本です。"
      ]
    },
    {
      "title": "立ち回りのコツ",
      "body": [
        "他機種と同じ感覚で、ゲーム数から座るページだと考えると、このページの意図とズレます。 設定狙いの補助ページとして割り切った方が使いやすいです。",
        "**設定1機械割97.7%・設定4で104.0%**のスペックのため、設定4以上をつかめれば長時間稼働で十分プラス収支を狙えます。イベント日や強い根拠がある日を前提に、初当たりや示唆を丁寧に拾っていく形が向いています。",
        "ポチポチくんで初当りや小役をカウントして設定判別を効率化しましょう。3000〜5000G程度のサンプルを積み、複数台のデータを比較しながら高設定候補を絞り込むのがコツです。",
        "示唆演出はボーナス・AT終了ごとに記録しておくと整理しやすいです。**紅葉トロフィー（設定5以上濃厚）**や**虹トロフィー（設定6濃厚）**といった強示唆が出た場合は閉店まで続行が基本です。"
      ]
    },
    {
      "title": "設定示唆まとめ",
      "type": "settei",
      "tables": [
        {
          "label": "確認ポイント",
          "headers": [
            "要素",
            "見方"
          ],
          "rows": [
            [
              "終了画面",
              {
                "text": "画像を残して比較",
                "badge": "weak"
              }
            ],
            [
              "小役確率",
              {
                "text": "ポチポチくんで管理",
                "badge": "mid"
              }
            ],
            [
              "初当たり",
              {
                "text": "複数回で判断",
                "badge": "weak"
              }
            ]
          ]
        }
      ]
    },
    {
      "title": "このページの役割",
      "body": [
        "この機種は、他機種のようにゲーム数から狙い目を出すページではありません。 記事ページでは、設定狙いの入口として扱います。",
        "上に出ている案内表示を確認したら、そのまま小役カウンターへ進む使い方が基本です。"
      ]
    },
    {
      "title": "使い方",
      "body": [
        "ゲーム数チェッカーとして使うのではなく、設定狙いの判断材料を集める前提で見てください。 初当たりや小役を積み上げる方が、この機種には合っています。",
        "上部と下部のボタンからポチポチくんへ進み、そちらで数値を蓄積していく流れが自然です。"
      ]
    },
    {
      "title": "区切り方",
      "body": [
        "このページはゲーム数狙いのヤメ時を見るためのものではありません。 設定狙いで区切るときは、示唆画面や小役カウントを取り切ったかを先に確認してください。",
        "高設定狙いで触った台ほど、ボーナスやAT終了後の示唆を見落とさず、ポチポチくん側の数値整理まで済ませてから区切る方が使いやすいです。"
      ]
    },
    {
      "type": "rumor",
      "title": "噂・未確定情報",
      "body": [
        "※以下は公式未発表・未確認の情報です。実際の挙動と異なる可能性があります。",
        "完全攻略時の設定1機械割は**103.4%**まで届くという解析がありますが、技術介入の難易度が高く、実戦値はそこから0.5〜1%程度下振れすると想定したほうが安全です。",
        "ボーナス終了後の音声が「ボーナスゲットでヘイ・ドゥーン」など特定パターンに変化すると高設定示唆という噂もありますが、メーカー公表のデータではないため、参考程度に留めてください。新情報が入り次第更新します。"
      ]
    }
  ]
}