{
  "slug": "valvrave",
  "name": "パチスロ 革命機ヴァルヴレイヴ",
  "sections": [
    {
      "title": "天井・恩恵",
      "body": [
        "天井は<strong>4系統</strong>の複合天井。メインは<strong>AT&ボーナス間1500G+α</strong>と<strong>CZ間1000G+α（液晶ゲーム数）</strong>の2本柱。",
        "① AT&ボーナス間天井: 実ゲーム数1500G+α消化でボーナス当選（AT中のゲーム数もカウント）",
        "② CZ間天井: 液晶表示のゲーム数で1000G+α消化でCZ当選",
        "③ CZスルー天井: CZを<strong>7回スルー</strong>で次回CZ当選時に成功濃厚",
        "④ 決戦ボーナス天井: 4連続でラッシュ非当選でラッシュ当選濃厚",
        "CZ間と実ゲーム数は別カウントになっているため、どちらを優先して把握するかで立ち回りが変わる。"
      ]
    },
    {
      "title": "狙い目",
      "body": [
        "<strong>AT&ボーナス間（実ゲーム数）での狙い目（等価）: 780G〜</strong>",
        "<strong>CZ間（液晶ゲーム数）での狙い目（等価）: 400G〜</strong>",
        "スルー回数が増えるほど狙い目ゲーム数が大幅に下がる：",
        "・0スルー: 400G〜 / 1スルー: 380G〜 / 2スルー: 150G〜 / 3スルー: 90G〜 / 4スルー以降: 80G〜",
        "金種別の目安（AT&ボーナス間）：",
        "・等価 / 5.6枚: <strong>780G〜</strong>",
        "・5.5枚: <strong>850G〜</strong>",
        "・5.0枚: <strong>930G〜</strong>",
        "・4.5枚: <strong>1000G〜</strong>"
      ]
    },
    {
      "title": "リセット・ヤメ時",
      "body": [
        "ヤメ時は状況によって異なる。ボーナス後は<strong>即ヤメ</strong>が基本。AT終了後は<strong>下パネルの明滅が消えるまで</strong>（引き戻しゾーン終了まで）続行してからヤメ。",
        "AT後の引き戻しゾーン（ミミズタイム）は最大66G+αで前兆の有無を確認してからヤメること。",
        "設定変更後の天井短縮については情報が少ないため、リセット台の優遇は不明。朝一台は履歴を確認してから判断すること。"
      ]
    },
    {
      "title": "設定示唆まとめ",
      "type": "settei",
      "rows": [
        { "left": "CZ「革命ラッシュ」の当選率", "right": "高設定ほど高い" },
        { "left": "決戦ボーナス中の演出・エピソード", "right": "内容・話数で設定示唆" },
        { "left": "AT終了画面", "right": "キャラクター・セリフ内容で示唆" },
        { "left": "機械割: 設定1 97.3% / 設定6 114.9%", "right": "6段階設定" }
      ]
    },
    {
      "title": "噂・未確定情報",
      "type": "rumor",
      "body": [
        "⚠ 以下は噂・未確定情報です。公式発表ではありません。",
        "「ミミズモード」と呼ばれる高確状態が存在し、この状態中はCZ間200〜300G付近でのゾーン期待度が高まるという情報がある。判別方法については諸説あり公式確認は未完了。",
        "CZ間ゲーム数カウントが液晶表示と内部カウントでズレる場合があるという報告が一部であるが、詳細は不明。"
      ]
    }
  ]
}
